geoparquet_io/__init__.py
geoparquet_io/cli.py
geoparquet_io/api/__init__.py
geoparquet_io/api/check.py
geoparquet_io/api/ops.py
geoparquet_io/api/pipeline.py
geoparquet_io/api/stac.py
geoparquet_io/api/table.py
geoparquet_io/cli/__init__.py
geoparquet_io/cli/decorators.py
geoparquet_io/cli/fix_helpers.py
geoparquet_io/cli/main.py
geoparquet_io/core/__init__.py
geoparquet_io/core/add_admin_divisions_multi.py
geoparquet_io/core/add_bbox_column.py
geoparquet_io/core/add_bbox_metadata.py
geoparquet_io/core/add_country_codes.py
geoparquet_io/core/add_h3_column.py
geoparquet_io/core/add_kdtree_column.py
geoparquet_io/core/add_quadkey_column.py
geoparquet_io/core/admin_datasets.py
geoparquet_io/core/arcgis.py
geoparquet_io/core/benchmark.py
geoparquet_io/core/check_fixes.py
geoparquet_io/core/check_parquet_structure.py
geoparquet_io/core/check_spatial_order.py
geoparquet_io/core/common.py
geoparquet_io/core/constants.py
geoparquet_io/core/convert.py
geoparquet_io/core/duckdb_metadata.py
geoparquet_io/core/extract.py
geoparquet_io/core/extract_bigquery.py
geoparquet_io/core/format_writers.py
geoparquet_io/core/geojson_stream.py
geoparquet_io/core/hilbert_order.py
geoparquet_io/core/inspect.py
geoparquet_io/core/inspect_utils.py
geoparquet_io/core/logging_config.py
geoparquet_io/core/metadata_utils.py
geoparquet_io/core/partition_admin_hierarchical.py
geoparquet_io/core/partition_by_h3.py
geoparquet_io/core/partition_by_kdtree.py
geoparquet_io/core/partition_by_quadkey.py
geoparquet_io/core/partition_by_string.py
geoparquet_io/core/partition_common.py
geoparquet_io/core/partition_reader.py
geoparquet_io/core/reproject.py
geoparquet_io/core/sort_by_column.py
geoparquet_io/core/sort_quadkey.py
geoparquet_io/core/split_by_country.py
geoparquet_io/core/stac.py
geoparquet_io/core/stac_check.py
geoparquet_io/core/stream_io.py
geoparquet_io/core/streaming.py
geoparquet_io/core/upload.py
geoparquet_io/core/validate.py
geoparquet_io-0.9.0.dist-info/METADATA
geoparquet_io-0.9.0.dist-info/WHEEL
geoparquet_io-0.9.0.dist-info/entry_points.txt
geoparquet_io-0.9.0.dist-info/licenses/LICENSE
geoparquet_io-0.9.0.dist-info/RECORD
