Metadata-Version: 2.4
Name: geoparquet-io
Version: 0.9.0
Summary: Fast I/O and transformation tools for GeoParquet files
Project-URL: Homepage, https://github.com/geoparquet/geoparquet-io
Project-URL: Bug Tracker, https://github.com/geoparquet/geoparquet-io/issues
Project-URL: Documentation, https://geoparquet.io/
Project-URL: Source, https://github.com/geoparquet/geoparquet-io
Author-email: Chris Holmes <cholmes@9eo.org>
License-Expression: Apache-2.0
License-File: LICENSE
Keywords: geoparquet,geospatial,gis,io,parquet
Classifier: Development Status :: 4 - Beta
Classifier: Intended Audience :: Developers
Classifier: Intended Audience :: Science/Research
Classifier: License :: OSI Approved :: Apache Software License
Classifier: Programming Language :: Python :: 3
Classifier: Programming Language :: Python :: 3.10
Classifier: Programming Language :: Python :: 3.11
Classifier: Programming Language :: Python :: 3.12
Classifier: Programming Language :: Python :: 3.13
Classifier: Topic :: Scientific/Engineering :: GIS
Requires-Python: >=3.10
Requires-Dist: aiohttp>=3.8.0
Requires-Dist: click>=8.0.0
Requires-Dist: duckdb>=1.4.1
Requires-Dist: fsspec>=2023.9.0
Requires-Dist: geoarrow-pyarrow>=0.1.0
Requires-Dist: httpx>=0.25.0
Requires-Dist: jsonschema>=4.0.0
Requires-Dist: mercantile>=1.2.0
Requires-Dist: obstore>=0.8.2
Requires-Dist: pandas>=1.0.0
Requires-Dist: psutil>=5.9.0
Requires-Dist: pyarrow<23.0.0,>=12.0.0
Requires-Dist: pyproj>=3.0.0
Requires-Dist: pystac>=1.9.0
Requires-Dist: rich>=13.0.0
Requires-Dist: s3fs>=2023.9.0
Provides-Extra: benchmark
Requires-Dist: fiona>=1.9.0; extra == 'benchmark'
Requires-Dist: geopandas>=0.14.0; extra == 'benchmark'
Requires-Dist: pyogrio>=0.7.0; extra == 'benchmark'
Provides-Extra: dev
Requires-Dist: mypy>=1.0.0; extra == 'dev'
Requires-Dist: nbmake>=1.5.0; extra == 'dev'
Requires-Dist: pre-commit>=4.3.0; extra == 'dev'
Requires-Dist: pytest-cov>=4.0.0; extra == 'dev'
Requires-Dist: pytest-xdist>=3.5.0; extra == 'dev'
Requires-Dist: pytest>=7.0.0; extra == 'dev'
Requires-Dist: radon>=6.0.1; extra == 'dev'
Requires-Dist: ruff>=0.8.0; extra == 'dev'
Requires-Dist: vulture>=2.14; extra == 'dev'
Requires-Dist: xenon>=0.9.3; extra == 'dev'
Provides-Extra: docs
Requires-Dist: mkdocs-material>=9.5.0; extra == 'docs'
Requires-Dist: mkdocs>=1.5.0; extra == 'docs'
Requires-Dist: mkdocstrings[python]>=0.24.0; extra == 'docs'
